setup.py
ftport/__init__.py
ftport.egg-info/PKG-INFO
ftport.egg-info/SOURCES.txt
ftport.egg-info/dependency_links.txt
ftport.egg-info/top_level.txt