Metadata-Version: 1.1
Name: ftport
Version: 0.0.2
Summary: Python ftplib extension for registering an alternative IP for the PORT command
Home-page: https://github.com/jgomo3/ftport
Author: Jesús Gómez
Author-email: jgomo3@gmail.com
License: MIT
Keywords: ftp-client ftp
Platform: UNKNOWN
Classifier: Development Status :: 3 - Alpha
Classifier: Intended Audience :: Developers
Classifier: Intended Audience :: System Administrators
Classifier: Topic :: Software Development :: Build Tools
Classifier: Topic :: Internet :: File Transfer Protocol (FTP)
Classifier: Topic :: Software Development :: Libraries :: Python Modules
Classifier: Topic :: System :: Systems Administration
Classifier: License :: OSI Approved :: MIT License
Classifier: Programming Language :: Python :: 3
